cxbuild/__about__.py
cxbuild/__init__.py
cxbuild/activity.py
cxbuild/backend.py
cxbuild/build_tool.py
cxbuild/cmake_extension.py
cxbuild/cmake_tool.py
cxbuild/copyutils.py
cxbuild/cxbuild.py
cxbuild/extension_builder.py
cxbuild/pip_tool.py
cxbuild/project.py
cxbuild/project_base.py
cxbuild/pyproject.py
cxbuild/setup_tool.py
cxbuild/solution.py
cxbuild/tool.py
cxbuild/cli/__init__.py
cxbuild-0.3.dist-info/METADATA
cxbuild-0.3.dist-info/WHEEL
cxbuild-0.3.dist-info/entry_points.txt
cxbuild-0.3.dist-info/licenses/LICENSE
cxbuild-0.3.dist-info/RECORD
