Metadata-Version: 2.1
Name: cxbuild
Version: 0.3
Summary: CMake Extension Builder
Project-URL: homepage, https://github.com/crungelab/cxbuild
Project-URL: documentation, https://crungelab.github.io/cxbuild/
Project-URL: repository, https://github.com/crungelab/cxbuild
Project-URL: changelog, https://github.com/crungelab/cxbuild/blob/main/CHANGELOG.md
Author-email: Kurtis Fields <kurtisfields@gmail.com>
License: MIT License
License-File: LICENSE
Classifier: Development Status :: 4 - Beta
Classifier: Programming Language :: Python
Classifier: Programming Language :: Python :: 3.8
Classifier: Programming Language :: Python :: 3.9
Classifier: Programming Language :: Python :: 3.10
Classifier: Programming Language :: Python :: Implementation :: CPython
Classifier: Programming Language :: Python :: Implementation :: PyPy
Requires-Python: >=3.8
Requires-Dist: build~=1.0.3
Requires-Dist: click~=8.1.7
Requires-Dist: loguru~=0.7.2
Requires-Dist: pydantic~=2.5.3
Requires-Dist: setuptools~=68.2.2
Requires-Dist: tomli~=2.0.1
Requires-Dist: wheel~=0.41.2
Provides-Extra: dev
Requires-Dist: black~=22.12.0; extra == 'dev'
Provides-Extra: test
Requires-Dist: pytest~=7.2.1; extra == 'test'
